<?xml version="1.0" encoding="UTF-8"?>
<Broker><CompiledApplication><ConfigurableProperty uri="startMode"/></CompiledApplication><CompiledMessageFlow name="mqsi.Response"><ConfigurableProperty uri="mqsi.Response#additionalInstances"/><ConfigurableProperty uri="mqsi.Response#commitCount"/><ConfigurableProperty uri="mqsi.Response#commitInterval"/><ConfigurableProperty uri="mqsi.Response#coordinatedTransaction"/><ConfigurableProperty uri="mqsi.Response#consumerPolicySet"/><ConfigurableProperty uri="mqsi.Response#providerPolicySet"/><ConfigurableProperty uri="mqsi.Response#consumerPolicySetBindings"/><ConfigurableProperty uri="mqsi.Response#providerPolicySetBindings"/><ConfigurableProperty uri="mqsi.Response#securityProfileName"/><ConfigurableProperty uri="mqsi.Response#monitoringProfile"/><ConfigurableProperty uri="mqsi.Response#startMode"/><ConfigurableProperty uri="mqsi.Response#startInstancesWhenFlowStarts"/><ConfigurableProperty override="no" uri="mqsi.Error#Build Error Message.connectDatasourceBeforeFlowStarts"/><ConfigurableProperty uri="mqsi.Error#Build Error Message.dataSource"/><ConfigurableProperty uri="mqsi.Error#Build Error Message.validateMaster"/><ConfigurableProperty override="no" uri="mqsi.Error#Create Error Response.connectDatasourceBeforeFlowStarts"/><ConfigurableProperty uri="mqsi.Error#Create Error Response.dataSource"/><ConfigurableProperty uri="mqsi.Error#Create Error Response.validateMaster"/><ConfigurableProperty override="" uri="mqsi.Error#Error Output.queueManagerName"/><ConfigurableProperty override="QLP.CONLEA.ERROR" uri="mqsi.Error#Error Output.queueName"/><ConfigurableProperty uri="mqsi.Error#Error Output.replyToQ"/><ConfigurableProperty uri="mqsi.Error#Error Output.replyToQMgr"/><ConfigurableProperty uri="mqsi.Error#Error Output.securityProfileName"/><ConfigurableProperty override="none" uri="mqsi.Error#Error Output.validateMaster"/><ConfigurableProperty override="no" uri="mqsi.Error#ErrorLoggingOn?.connectDatasourceBeforeFlowStarts"/><ConfigurableProperty uri="mqsi.Error#ErrorLoggingOn?.dataSource"/><ConfigurableProperty override="no" uri="mqsi.Error#Reply if Request Mode.connectDatasourceBeforeFlowStarts"/><ConfigurableProperty uri="mqsi.Error#Reply if Request Mode.dataSource"/><ConfigurableProperty uri="mqsi.Error#Reply.validateMaster"/><ConfigurableProperty override="no" uri="mqsi.Log#Create Log Message.connectDatasourceBeforeFlowStarts"/><ConfigurableProperty uri="mqsi.Log#Create Log Message.dataSource"/><ConfigurableProperty uri="mqsi.Log#Create Log Message.validateMaster"/><ConfigurableProperty override="no" uri="mqsi.Log#Create Trace Data.connectDatasourceBeforeFlowStarts"/><ConfigurableProperty uri="mqsi.Log#Create Trace Data.dataSource"/><ConfigurableProperty uri="mqsi.Log#Create Trace Data.validateMaster"/><ConfigurableProperty override="no" uri="mqsi.Log#Logging On?.connectDatasourceBeforeFlowStarts"/><ConfigurableProperty uri="mqsi.Log#Logging On?.dataSource"/><ConfigurableProperty uri="mqsi.Log#Trace.filePath"/><ConfigurableProperty override="" uri="mqsi.Log#Write Log.queueManagerName"/><ConfigurableProperty override="QLP.CONLEA.LOG" uri="mqsi.Log#Write Log.queueName"/><ConfigurableProperty uri="mqsi.Log#Write Log.replyToQ"/><ConfigurableProperty uri="mqsi.Log#Write Log.replyToQMgr"/><ConfigurableProperty uri="mqsi.Log#Write Log.securityProfileName"/><ConfigurableProperty override="none" uri="mqsi.Log#Write Log.validateMaster"/><ConfigurableProperty override="no" uri="mqsi.Response#Compute.connectDatasourceBeforeFlowStarts"/><ConfigurableProperty uri="mqsi.Response#Compute.dataSource"/><ConfigurableProperty uri="mqsi.Response#Compute.validateMaster"/><ConfigurableProperty override="true" uri="mqsi.Response#ErrorLoggingOn"/><ConfigurableProperty override="no" uri="mqsi.Response#Initialise.connectDatasourceBeforeFlowStarts"/><ConfigurableProperty uri="mqsi.Response#Initialise.dataSource"/><ConfigurableProperty uri="mqsi.Response#Initialise.validateMaster"/><ConfigurableProperty uri="mqsi.Response#MQ Header.mqdlhDestQMgrName"/><ConfigurableProperty uri="mqsi.Response#MQ Header.mqdlhDestQName"/><ConfigurableProperty override="Inherit" uri="mqsi.Response#MQ Header.mqmdReplyToQ"/><ConfigurableProperty override="Inherit" uri="mqsi.Response#MQ Header.mqmdReplyToQMgr"/><ConfigurableProperty override="no" uri="mqsi.Response#MQ Warning.connectDatasourceBeforeFlowStarts"/><ConfigurableProperty uri="mqsi.Response#MQ Warning.dataSource"/><ConfigurableProperty uri="mqsi.Response#MQ Warning.validateMaster"/><ConfigurableProperty override="no" uri="mqsi.Response#Missing Stored Msg.connectDatasourceBeforeFlowStarts"/><ConfigurableProperty uri="mqsi.Response#Missing Stored Msg.dataSource"/><ConfigurableProperty uri="mqsi.Response#Missing Stored Msg.validateMaster"/><ConfigurableProperty uri="mqsi.Response#Read Response.additionalInstances"/><ConfigurableProperty uri="mqsi.Response#Read Response.componentLevel"/><ConfigurableProperty override="QLP.CONLEA.RESP" uri="mqsi.Response#Read Response.queueName"/><ConfigurableProperty uri="mqsi.Response#Read Response.resetBrowseTimeout"/><ConfigurableProperty uri="mqsi.Response#Read Response.securityProfileName"/><ConfigurableProperty uri="mqsi.Response#Read Response.serializationToken"/><ConfigurableProperty uri="mqsi.Response#Read Response.topicProperty"/><ConfigurableProperty uri="mqsi.Response#Read Response.validateMaster"/><ConfigurableProperty uri="mqsi.Response#Reply.validateMaster"/><ConfigurableProperty override="/pr/Leasing/Configuracion/AppConfig.xml" uri="mqsi.Response#Response Processor.ENTORNO"/><ConfigurableProperty override="true" uri="mqsi.Response#ResponseLoggingOn"/><ConfigurableProperty override="QLP.CONLEA.STORE" uri="mqsi.Response#Retrieve.queueName"/><ConfigurableProperty uri="mqsi.Response#Retrieve.validateMaster"/><ConfigurableProperty uri="mqsi.ResponseProcessor#Appconfig.javaClassLoader"/><ConfigurableProperty uri="mqsi.ResponseProcessor#Appconfig.validateMaster"/><ConfigurableProperty uri="mqsi.ResponseProcessor#Correlación de WTX.CacheMap"/><ConfigurableProperty override="1" uri="mqsi.ResponseProcessor#Correlación de WTX.CardNoToWire"/><ConfigurableProperty uri="mqsi.ResponseProcessor#Correlación de WTX.MapServerLocation"/><ConfigurableProperty override="true" uri="mqsi.ResponseProcessor#Error.ErrorLoggingOn"/><ConfigurableProperty override="no" uri="mqsi.ResponseProcessor#Set Operacion.connectDatasourceBeforeFlowStarts"/><ConfigurableProperty uri="mqsi.ResponseProcessor#Set Operacion.dataSource"/><ConfigurableProperty uri="mqsi.ResponseProcessor#Set Operacion.validateMaster"/><ConfigurableProperty override="no" uri="mqsi.ResponseProcessor#SetMSG.connectDatasourceBeforeFlowStarts"/><ConfigurableProperty uri="mqsi.ResponseProcessor#SetMSG.dataSource"/><ConfigurableProperty uri="mqsi.ResponseProcessor#SetMSG.validateMaster"/></CompiledMessageFlow><CompiledMessageFlow name="mqsi.LeerLog"><ConfigurableProperty uri="mqsi.LeerLog#additionalInstances"/><ConfigurableProperty uri="mqsi.LeerLog#commitCount"/><ConfigurableProperty uri="mqsi.LeerLog#commitInterval"/><ConfigurableProperty uri="mqsi.LeerLog#coordinatedTransaction"/><ConfigurableProperty uri="mqsi.LeerLog#consumerPolicySet"/><ConfigurableProperty uri="mqsi.LeerLog#providerPolicySet"/><ConfigurableProperty uri="mqsi.LeerLog#consumerPolicySetBindings"/><ConfigurableProperty uri="mqsi.LeerLog#providerPolicySetBindings"/><ConfigurableProperty uri="mqsi.LeerLog#securityProfileName"/><ConfigurableProperty uri="mqsi.LeerLog#monitoringProfile"/><ConfigurableProperty uri="mqsi.LeerLog#startMode"/><ConfigurableProperty uri="mqsi.LeerLog#startInstancesWhenFlowStarts"/><ConfigurableProperty uri="mqsi.LeerLog#Java Compute.javaClassLoader"/><ConfigurableProperty uri="mqsi.LeerLog#Java Compute.validateMaster"/><ConfigurableProperty override="/pr/Leasing/Configuracion/AppConfig.xml" uri="mqsi.LeerLog#LOG"/><ConfigurableProperty uri="mqsi.LeerLog#MQ Input.additionalInstances"/><ConfigurableProperty uri="mqsi.LeerLog#MQ Input.componentLevel"/><ConfigurableProperty override="QLP.CONLEA.LOG" uri="mqsi.LeerLog#MQ Input.queueName"/><ConfigurableProperty uri="mqsi.LeerLog#MQ Input.resetBrowseTimeout"/><ConfigurableProperty uri="mqsi.LeerLog#MQ Input.securityProfileName"/><ConfigurableProperty uri="mqsi.LeerLog#MQ Input.serializationToken"/><ConfigurableProperty uri="mqsi.LeerLog#MQ Input.topicProperty"/><ConfigurableProperty uri="mqsi.LeerLog#MQ Input.validateMaster"/><ConfigurableProperty override="/log/as400/LogGeneral/log_Flujo.log" uri="mqsi.LeerLog#Trace.filePath"/><ConfigurableProperty override="/log/as400/LogGeneral/log_Flujo.log" uri="mqsi.LeerLog#Trace1.filePath"/></CompiledMessageFlow><CompiledMessageFlow name="mqsi.Request"><ConfigurableProperty uri="mqsi.Request#additionalInstances"/><ConfigurableProperty uri="mqsi.Request#commitCount"/><ConfigurableProperty uri="mqsi.Request#commitInterval"/><ConfigurableProperty uri="mqsi.Request#coordinatedTransaction"/><ConfigurableProperty uri="mqsi.Request#consumerPolicySet"/><ConfigurableProperty uri="mqsi.Request#providerPolicySet"/><ConfigurableProperty uri="mqsi.Request#consumerPolicySetBindings"/><ConfigurableProperty uri="mqsi.Request#providerPolicySetBindings"/><ConfigurableProperty uri="mqsi.Request#securityProfileName"/><ConfigurableProperty uri="mqsi.Request#monitoringProfile"/><ConfigurableProperty uri="mqsi.Request#startMode"/><ConfigurableProperty uri="mqsi.Request#startInstancesWhenFlowStarts"/><ConfigurableProperty override="no" uri="mqsi.Error#Build Error Message.connectDatasourceBeforeFlowStarts"/><ConfigurableProperty uri="mqsi.Error#Build Error Message.dataSource"/><ConfigurableProperty uri="mqsi.Error#Build Error Message.validateMaster"/><ConfigurableProperty override="no" uri="mqsi.Error#Create Error Response.connectDatasourceBeforeFlowStarts"/><ConfigurableProperty uri="mqsi.Error#Create Error Response.dataSource"/><ConfigurableProperty uri="mqsi.Error#Create Error Response.validateMaster"/><ConfigurableProperty override="" uri="mqsi.Error#Error Output.queueManagerName"/><ConfigurableProperty override="QLP.CONLEA.ERROR" uri="mqsi.Error#Error Output.queueName"/><ConfigurableProperty uri="mqsi.Error#Error Output.replyToQ"/><ConfigurableProperty uri="mqsi.Error#Error Output.replyToQMgr"/><ConfigurableProperty uri="mqsi.Error#Error Output.securityProfileName"/><ConfigurableProperty override="none" uri="mqsi.Error#Error Output.validateMaster"/><ConfigurableProperty override="no" uri="mqsi.Error#ErrorLoggingOn?.connectDatasourceBeforeFlowStarts"/><ConfigurableProperty uri="mqsi.Error#ErrorLoggingOn?.dataSource"/><ConfigurableProperty override="no" uri="mqsi.Error#Reply if Request Mode.connectDatasourceBeforeFlowStarts"/><ConfigurableProperty uri="mqsi.Error#Reply if Request Mode.dataSource"/><ConfigurableProperty uri="mqsi.Error#Reply.validateMaster"/><ConfigurableProperty override="no" uri="mqsi.Log#Create Log Message.connectDatasourceBeforeFlowStarts"/><ConfigurableProperty uri="mqsi.Log#Create Log Message.dataSource"/><ConfigurableProperty uri="mqsi.Log#Create Log Message.validateMaster"/><ConfigurableProperty override="no" uri="mqsi.Log#Create Trace Data.connectDatasourceBeforeFlowStarts"/><ConfigurableProperty uri="mqsi.Log#Create Trace Data.dataSource"/><ConfigurableProperty uri="mqsi.Log#Create Trace Data.validateMaster"/><ConfigurableProperty override="no" uri="mqsi.Log#Logging On?.connectDatasourceBeforeFlowStarts"/><ConfigurableProperty uri="mqsi.Log#Logging On?.dataSource"/><ConfigurableProperty uri="mqsi.Log#Trace.filePath"/><ConfigurableProperty override="" uri="mqsi.Log#Write Log.queueManagerName"/><ConfigurableProperty override="QLP.CONLEA.LOG" uri="mqsi.Log#Write Log.queueName"/><ConfigurableProperty uri="mqsi.Log#Write Log.replyToQ"/><ConfigurableProperty uri="mqsi.Log#Write Log.replyToQMgr"/><ConfigurableProperty uri="mqsi.Log#Write Log.securityProfileName"/><ConfigurableProperty override="none" uri="mqsi.Log#Write Log.validateMaster"/><ConfigurableProperty uri="mqsi.Request#Add Reply Address.mqdlhDestQMgrName"/><ConfigurableProperty uri="mqsi.Request#Add Reply Address.mqdlhDestQName"/><ConfigurableProperty override="QRP.CONLEA.RESP.QMCPSOA1" uri="mqsi.Request#Add Reply Address.mqmdReplyToQ"/><ConfigurableProperty override="QMPCLAS4" uri="mqsi.Request#Add Reply Address.mqmdReplyToQMgr"/><ConfigurableProperty override="true" uri="mqsi.Request#ErrorLoggingOn"/><ConfigurableProperty override="no" uri="mqsi.Request#Extract Original MQMD.connectDatasourceBeforeFlowStarts"/><ConfigurableProperty uri="mqsi.Request#Extract Original MQMD.dataSource"/><ConfigurableProperty uri="mqsi.Request#Extract Original MQMD.validateMaster"/><ConfigurableProperty override="" uri="mqsi.Request#Propagate Request.queueManagerName"/><ConfigurableProperty override="QRP.REQ.LEA.QMPCLAS4" uri="mqsi.Request#Propagate Request.queueName"/><ConfigurableProperty uri="mqsi.Request#Propagate Request.replyToQ"/><ConfigurableProperty uri="mqsi.Request#Propagate Request.replyToQMgr"/><ConfigurableProperty uri="mqsi.Request#Propagate Request.securityProfileName"/><ConfigurableProperty override="none" uri="mqsi.Request#Propagate Request.validateMaster"/><ConfigurableProperty uri="mqsi.Request#Read Request.additionalInstances"/><ConfigurableProperty uri="mqsi.Request#Read Request.componentLevel"/><ConfigurableProperty override="QLP.CONLEA.ENVIO" uri="mqsi.Request#Read Request.queueName"/><ConfigurableProperty uri="mqsi.Request#Read Request.resetBrowseTimeout"/><ConfigurableProperty uri="mqsi.Request#Read Request.securityProfileName"/><ConfigurableProperty uri="mqsi.Request#Read Request.serializationToken"/><ConfigurableProperty uri="mqsi.Request#Read Request.topicProperty"/><ConfigurableProperty uri="mqsi.Request#Read Request.validateMaster"/><ConfigurableProperty override="true" uri="mqsi.Request#RequestLoggingOn"/><ConfigurableProperty uri="mqsi.Request#Save to Store.queueManagerName"/><ConfigurableProperty override="QLP.CONLEA.STORE" uri="mqsi.Request#Save to Store.queueName"/><ConfigurableProperty uri="mqsi.Request#Save to Store.replyToQ"/><ConfigurableProperty uri="mqsi.Request#Save to Store.replyToQMgr"/><ConfigurableProperty uri="mqsi.Request#Save to Store.securityProfileName"/><ConfigurableProperty uri="mqsi.Request#Save to Store.validateMaster"/><ConfigurableProperty override="no" uri="mqsi.Request#Set Request Mode.connectDatasourceBeforeFlowStarts"/><ConfigurableProperty uri="mqsi.Request#Set Request Mode.dataSource"/><ConfigurableProperty uri="mqsi.Request#Set Request Mode.validateMaster"/><ConfigurableProperty uri="mqsi.Request#Store Reply Address.mqdlhDestQMgrName"/><ConfigurableProperty uri="mqsi.Request#Store Reply Address.mqdlhDestQName"/><ConfigurableProperty override="QRP.CONLEA.RESP.MQP4" uri="mqsi.Request#Store Reply Address.mqmdReplyToQ"/><ConfigurableProperty override="QMCPSOA1" uri="mqsi.Request#Store Reply Address.mqmdReplyToQMgr"/><ConfigurableProperty override="no" uri="mqsi.RequestProcessor#Compute.connectDatasourceBeforeFlowStarts"/><ConfigurableProperty uri="mqsi.RequestProcessor#Compute.dataSource"/><ConfigurableProperty uri="mqsi.RequestProcessor#Compute.validateMaster"/></CompiledMessageFlow><CompiledMessageFlow name="mqsi.LeerError"><ConfigurableProperty uri="mqsi.LeerError#additionalInstances"/><ConfigurableProperty uri="mqsi.LeerError#commitCount"/><ConfigurableProperty uri="mqsi.LeerError#commitInterval"/><ConfigurableProperty uri="mqsi.LeerError#coordinatedTransaction"/><ConfigurableProperty uri="mqsi.LeerError#consumerPolicySet"/><ConfigurableProperty uri="mqsi.LeerError#providerPolicySet"/><ConfigurableProperty uri="mqsi.LeerError#consumerPolicySetBindings"/><ConfigurableProperty uri="mqsi.LeerError#providerPolicySetBindings"/><ConfigurableProperty uri="mqsi.LeerError#securityProfileName"/><ConfigurableProperty uri="mqsi.LeerError#monitoringProfile"/><ConfigurableProperty uri="mqsi.LeerError#startMode"/><ConfigurableProperty uri="mqsi.LeerError#startInstancesWhenFlowStarts"/><ConfigurableProperty uri="mqsi.LeerError#MQ Input.additionalInstances"/><ConfigurableProperty uri="mqsi.LeerError#MQ Input.componentLevel"/><ConfigurableProperty override="QLP.CONLEA.ERROR" uri="mqsi.LeerError#MQ Input.queueName"/><ConfigurableProperty uri="mqsi.LeerError#MQ Input.resetBrowseTimeout"/><ConfigurableProperty uri="mqsi.LeerError#MQ Input.securityProfileName"/><ConfigurableProperty uri="mqsi.LeerError#MQ Input.serializationToken"/><ConfigurableProperty uri="mqsi.LeerError#MQ Input.topicProperty"/><ConfigurableProperty uri="mqsi.LeerError#MQ Input.validateMaster"/><ConfigurableProperty override="/log/as400/errorFlujo/log_Flujo.log" uri="mqsi.LeerError#Trace.filePath"/></CompiledMessageFlow></Broker>